easysearch
