Metadata-Version: 1.0
Name: easysearch
Version: 0.0.19
Summary: Machine learning library for Easysearch
Home-page: http://github.com/DataEasy/easysearch
Author: Pedro Castro
Author-email: pedro.castro@dataeasy.com.br
License: UNKNOWN
Platform: UNKNOWN
